<annotation verified="yes">
    <folder>Annotation</folder>
    <filename>123143_05-11_categorie_1.jpg</filename>
    <path>Crabs-PascalVOC-export/Annotations/123143_05-11_categorie_1.jpg</path>
    <source>
        <database>Unknown</database>
    </source>
    <size>
        <width>2592</width>
        <height>1944</height>
        <depth>3</depth>
    </size>
    <segmented>0</segmented>
    <object>
    <name>Crab</name>
    <pose>Unspecified</pose>
    <truncated>0</truncated>
    <difficult>0</difficult>
    <bndbox>
        <xmin>1054.8601252609603</xmin>
        <ymin>604.3186960034384</ymin>
        <xmax>1219.362806220642</xmax>
        <ymax>771.1019994369125</ymax>
    </bndbox>
</object><object>
    <name>Crab</name>
    <pose>Unspecified</pose>
    <truncated>0</truncated>
    <difficult>0</difficult>
    <bndbox>
        <xmin>1520.2296450939457</xmin>
        <ymin>610.8167296173181</ymin>
        <xmax>1654.4291615018267</xmax>
        <ymax>771.1019994369124</ymax>
    </bndbox>
</object><object>
    <name>Crab</name>
    <pose>Unspecified</pose>
    <truncated>0</truncated>
    <difficult>0</difficult>
    <bndbox>
        <xmin>1697.7193493932673</xmin>
        <ymin>979.0395708429448</ymin>
        <xmax>1842.74157791297</xmax>
        <ymax>1143.6568906141192</ymax>
    </bndbox>
</object><object>
    <name>Crab</name>
    <pose>Unspecified</pose>
    <truncated>0</truncated>
    <difficult>0</difficult>
    <bndbox>
        <xmin>1734.5161081843685</xmin>
        <ymin>1423.0730796537691</ymin>
        <xmax>1903.3477418776097</xmax>
        <ymax>1609.3504839288823</ymax>
    </bndbox>
</object><object>
    <name>Crab</name>
    <pose>Unspecified</pose>
    <truncated>0</truncated>
    <difficult>0</difficult>
    <bndbox>
        <xmin>1842.74157791297</xmin>
        <ymin>1199.9732921037169</ymin>
        <xmax>1972.6121415872915</xmax>
        <ymax>1355.9264293447509</ymax>
    </bndbox>
</object>
</annotation>
