<annotation verified="yes">
    <folder>Annotation</folder>
    <filename>133310_05-11_categorie_3.jpg</filename>
    <path>Crabs-PascalVOC-export/Annotations/133310_05-11_categorie_3.jpg</path>
    <source>
        <database>Unknown</database>
    </source>
    <size>
        <width>2592</width>
        <height>1944</height>
        <depth>3</depth>
    </size>
    <segmented>0</segmented>
    <object>
    <name>Crab</name>
    <pose>Unspecified</pose>
    <truncated>0</truncated>
    <difficult>0</difficult>
    <bndbox>
        <xmin>1619.7970442164667</xmin>
        <ymin>1379.7527453919306</ymin>
        <xmax>1831.9190309401097</xmax>
        <ymax>1585.5243331356633</ymax>
    </bndbox>
</object><object>
    <name>Crab</name>
    <pose>Unspecified</pose>
    <truncated>0</truncated>
    <difficult>0</difficult>
    <bndbox>
        <xmin>1890.36071853797</xmin>
        <ymin>1472.891364902507</ymin>
        <xmax>2098.1537525280532</xmax>
        <ymax>1641.8407346252611</ymax>
    </bndbox>
</object><object>
    <name>Crab</name>
    <pose>Unspecified</pose>
    <truncated>0</truncated>
    <difficult>0</difficult>
    <bndbox>
        <xmin>1585.1649269311065</xmin>
        <ymin>314.0724233983287</ymin>
        <xmax>1847.0705306465293</xmax>
        <ymax>496.01786034884225</ymax>
    </bndbox>
</object><object>
    <name>Crab</name>
    <pose>Unspecified</pose>
    <truncated>0</truncated>
    <difficult>0</difficult>
    <bndbox>
        <xmin>950.9636082659187</xmin>
        <ymin>437.5353925699643</ymin>
        <xmax>1202.0468301474427</xmax>
        <ymax>593.4886124379788</ymax>
    </bndbox>
</object><object>
    <name>Crab</name>
    <pose>Unspecified</pose>
    <truncated>0</truncated>
    <difficult>0</difficult>
    <bndbox>
        <xmin>1009.4054610027401</xmin>
        <ymin>1726.3154194866381</ymin>
        <xmax>1241.0079001663623</xmax>
        <ymax>1929.9208583141103</ymax>
    </bndbox>
</object><object>
    <name>Crab</name>
    <pose>Unspecified</pose>
    <truncated>0</truncated>
    <difficult>0</difficult>
    <bndbox>
        <xmin>691.2224809172756</xmin>
        <ymin>1579.0262168948032</ymin>
        <xmax>924.9895615866388</xmax>
        <ymax>1815.1220716726148</ymax>
    </bndbox>
</object>
</annotation>
