<annotation verified="yes">
    <folder>Annotation</folder>
    <filename>140001_05-11_categorie_4.jpg</filename>
    <path>Crabs-PascalVOC-export/Annotations/140001_05-11_categorie_4.jpg</path>
    <source>
        <database>Unknown</database>
    </source>
    <size>
        <width>2592</width>
        <height>1944</height>
        <depth>3</depth>
    </size>
    <segmented>0</segmented>
    <object>
    <name>Crab</name>
    <pose>Unspecified</pose>
    <truncated>0</truncated>
    <difficult>0</difficult>
    <bndbox>
        <xmin>1524.2881002087684</xmin>
        <ymin>1639.6747509629613</ymin>
        <xmax>1764.548609978471</xmax>
        <ymax>1901.7627401962918</ymax>
    </bndbox>
</object>
</annotation>
