<annotation verified="yes">
    <folder>Annotation</folder>
    <filename>150310_05-11_categorie_3.jpg</filename>
    <path>Crabs-PascalVOC-export/Annotations/150310_05-11_categorie_3.jpg</path>
    <source>
        <database>Unknown</database>
    </source>
    <size>
        <width>2592</width>
        <height>1944</height>
        <depth>3</depth>
    </size>
    <segmented>0</segmented>
    <object>
    <name>Crab</name>
    <pose>Unspecified</pose>
    <truncated>0</truncated>
    <difficult>0</difficult>
    <bndbox>
        <xmin>1500.4785298962684</xmin>
        <ymin>1130.6607407593795</ymin>
        <xmax>1857.6225800006525</xmax>
        <ymax>1332.100278551532</ymax>
    </bndbox>
</object><object>
    <name>Crab</name>
    <pose>Unspecified</pose>
    <truncated>0</truncated>
    <difficult>0</difficult>
    <bndbox>
        <xmin>1102.2087682672234</xmin>
        <ymin>688.7932982378351</ymin>
        <xmax>1318.659707724426</xmax>
        <ymax>879.4028350915085</ymax>
    </bndbox>
</object>
</annotation>
