<annotation verified="yes">
    <folder>Annotation</folder>
    <filename>H_D_mirror%20(104).jpg</filename>
    <path>Crabs-PascalVOC-export/Annotations/H_D_mirror%20(104).jpg</path>
    <source>
        <database>Unknown</database>
    </source>
    <size>
        <width>2592</width>
        <height>1944</height>
        <depth>3</depth>
    </size>
    <segmented>0</segmented>
    <object>
    <name>Crab</name>
    <pose>Unspecified</pose>
    <truncated>0</truncated>
    <difficult>0</difficult>
    <bndbox>
        <xmin>631.157477329071</xmin>
        <ymin>426.70530900450467</ymin>
        <xmax>1126.8299965748956</xmax>
        <ymax>935.7192365811063</ymax>
    </bndbox>
</object><object>
    <name>Crab</name>
    <pose>Unspecified</pose>
    <truncated>0</truncated>
    <difficult>0</difficult>
    <bndbox>
        <xmin>51.06889352818372</xmin>
        <ymin>866.4066852367688</ymin>
        <xmax>538.0835073068894</xmax>
        <ymax>1332.100278551532</ymax>
    </bndbox>
</object>
</annotation>
